<!DOCTYPE Job SYSTEM "job.dtd">
<Job ShortName="BCpt">
    <Description>
        She will go out into the wilds to capture beasts.
    </Description>
    <Performance>
        <Factor Skill="AnimalHandling" Weight="2"/>
        <Factor Skill="Combat" Weight="2"/>
        <Factor Stat="Strength" Weight="2"/>
        <Factor Skill="Beastiality" Weight="1"/>
        <Factor Skill="Magic" Weight="1"/>
        <Factor Stat="Agility" Weight="1"/>
        <Factor Stat="Constitution" Weight="1"/>

        <Trait Name="Hunter" Value="40"/>
        <Trait Name="Adventurer" Value="10"/>
        <Trait Name="Angel" Value="5"/>
        <Trait Name="Agile" Value="5"/>
        <Trait Name="Aggressive" Value="5"/>
    </Performance>

    <Gains XP="10" Skill="3">
        <Skill Name="AnimalHandling" Weight="2"/>
        <Stat Name="Strength" Weight="2"/>
        <Skill Name="Combat" Weight="2"/>
        <Stat Name="Agility" Weight="1"/>
        <Stat Name="Constitution" Weight="1"/>

        <GainTrait Trait="Tough" Threshold="30" Action="COMBAT">
            She has become pretty Tough from all of the fights she's been in.
        </GainTrait>
        <GainTrait Trait="Adventurer" Threshold="40" Action="COMBAT">
            She has been in enough tough spots to consider herself Adventurer.
        </GainTrait>
        <GainTrait Trait="Aggressive" Threshold="50" Action="COMBAT" Event="2">
            She is getting rather Aggressive from her enjoyment of combat.
        </GainTrait>
        <LoseTrait Trait="Fragile" Threshold="15" Action="COMBAT">
            ${name} has had to heal from so many injuries you can't say she is fragile anymore.
        </LoseTrait>
    </Gains>

    <Messages>
        <Message Name="work">
            <Text>${name} equipped herself and went out to hunt for exotic beasts and animals.</Text>
        </Message>
        <Message Name="refuse">
            <Text>${name} refused to capture beasts during the ${shift} shift.</Text>
        </Message>
    </Messages>
</Job>
