<Screen>
<Window     Name="Preparing Game"                                           XPos="796"      YPos="236"       Width="2249"     Height="1688" Border="1"  />
<Image      Name="Background"           File="building_mgt_bg.jpg"          XPos="0"        YPos="0"        Width="2249"     Height="1688"  />
<Text       Name="Text1"                Text=""                             XPos="281"      YPos="56"       Width="2249"     Height="169"  FontSize="84"  />
<Text       Name="Text2"                Text=""                             XPos="281"      YPos="169"       Width="562"     Height="1406" FontSize="42"  />
<Text       Name="Text3"                Text=""                             XPos="843"      YPos="281"      Width="843"     Height="84"  FontSize="42"  />
<Text       Name="Text4"                Text=""                             XPos="843"      YPos="394"      Width="843"     Height="84"  FontSize="42"  />
<Text       Name="Text5"                Text=""                             XPos="843"      YPos="506"      Width="843"     Height="84"  FontSize="42"  />
<!--                                                                                        
<Slider     Name="Counter1"                                                 XPos="843"      YPos="788"      Width="1124"     MinValue="0" MaxValue="100"      Value="0"      Increment="1"      LiveUpdate="true"      Hidden="false"      Disabled="false"       />
<Slider     Name="Counter2"                                                 XPos="843"      YPos="844"      Width="1124"     MinValue="0" MaxValue="100"      Value="0"      Increment="1"      LiveUpdate="true"      Hidden="false"      Disabled="false"       />
<Slider     Name="Counter3"                                                 XPos="843"      YPos="900"      Width="1124"     MinValue="0" MaxValue="100"      Value="0"      Increment="1"      LiveUpdate="true"      Hidden="false"      Disabled="false"       />
<Slider     Name="Counter4"                                                 XPos="843"      YPos="956"      Width="1124"     MinValue="0" MaxValue="100"      Value="0"      Increment="1"      LiveUpdate="true"      Hidden="false"      Disabled="false"       />
<Slider     Name="Counter5"                                                 XPos="843"      YPos="1012"      Width="1124"     MinValue="0" MaxValue="100"      Value="0"      Increment="1"      LiveUpdate="true"      Hidden="false"      Disabled="false"       />
-->                                                                                         
<Button     Name="BackButton"           Image="Back"                        XPos="1237"      YPos="1491"      Width="450"     Height="90"  Transparency="true" Scale="true"  />

</Screen>
